census_error_analyzer/__init__.py
census_error_analyzer-0.0.5.dist-info/LICENSE
census_error_analyzer-0.0.5.dist-info/METADATA
census_error_analyzer-0.0.5.dist-info/WHEEL
census_error_analyzer-0.0.5.dist-info/top_level.txt
census_error_analyzer-0.0.5.dist-info/RECORD
