Metadata-Version: 2.1
Name: census-error-analyzer
Version: 0.0.5
Summary: Analyze the margin of error in U.S. census data
License: MIT
Project-URL: Maintainer, https://github.com/datadesk
Project-URL: Source, https://github.com/datadesk/census-error-analyzer
Project-URL: Tracker, https://github.com/datadesk/census-error-analyzer/issues
Classifier: Development Status :: 5 - Production/Stable
Classifier: Programming Language :: Python
Classifier: Programming Language :: Python :: 3.7
Classifier: Programming Language :: Python :: 3.8
Classifier: Programming Language :: Python :: 3.9
Classifier: Programming Language :: Python :: 3.10
Classifier: Programming Language :: Python :: 3 :: Only
Classifier: License :: OSI Approved :: MIT License
Classifier: Topic :: Scientific/Engineering :: Mathematics
License-File: LICENSE
